pytest_flask_ligand/__init__.py
pytest_flask_ligand/py.typed
pytest_flask_ligand-0.1.14.data/data/README.rst/README.rst
pytest_flask_ligand-0.1.14.data/data/pytest_flask_ligand/py.typed/py.typed
pytest_flask_ligand-0.1.14.dist-info/AUTHORS
pytest_flask_ligand-0.1.14.dist-info/LICENSE
pytest_flask_ligand-0.1.14.dist-info/METADATA
pytest_flask_ligand-0.1.14.dist-info/WHEEL
pytest_flask_ligand-0.1.14.dist-info/entry_points.txt
pytest_flask_ligand-0.1.14.dist-info/pbr.json
pytest_flask_ligand-0.1.14.dist-info/top_level.txt
pytest_flask_ligand-0.1.14.dist-info/RECORD
