Metadata-Version: 2.1
Name: pytest-flask-ligand
Version: 0.1.14
Summary: Pytest fixtures and helper functions to use for testing flask-ligand microservices.
Author: Ryan Gard
Author-email: ryan@gardiancapitol.com
License: GNU General Public License v3 (GPLv3)
Project-URL: Changelog, https://github.com/cowofevil/pytest-flask-ligand/blob/main/CHANGELOG.md
Project-URL: Source, https://github.com/cowofevil/pytest-flask-ligand
Project-URL: Tracker, https://github.com/cowofevil/pytest-flask-ligand/issues
Keywords: test, unittest
Classifier: Development Status :: 4 - Beta
Classifier: Intended Audience :: Developers
Classifier: Framework :: Pytest
Classifier: Operating System :: MacOS :: MacOS X
Classifier: Operating System :: Microsoft :: Windows
Classifier: Operating System :: POSIX
Classifier: Natural Language :: English
Classifier: Programming Language :: Python :: 3
Classifier: Programming Language :: Python :: 3 :: Only
Classifier: Programming Language :: Python :: 3.10
Classifier: Programming Language :: Python :: 3.11
Classifier: Topic :: Software Development :: Libraries
Classifier: Topic :: Software Development :: Testing
Classifier: Topic :: Utilities
Classifier: Typing :: Typed
Requires-Python: >=3.10
License-File: LICENSE
License-File: AUTHORS
Requires-Dist: flask (~=2.2)
Requires-Dist: pytest (~=7.3)
Requires-Dist: python-dateutil (~=2.8)
